rtl/common/prbs15_gen.sv
module prbs15_gen #(
    parameter logic [14:0] SEED = 15'h0001
) (
    input logic clk,
    input logic rst,
    input logic load_seed,
    input logic advance,
    output logic bit_out,
    output logic [14:0] state
);

logic feedback;

assign bit_out = state[14];
assign feedback = state[14] ^ state[13];

always_ff @(posedge clk) begin
    if (rst) begin
        state <= SEED;
    end else if (load_seed) begin
        state <= SEED;
    end else if (state == 15'b0) begin
        state <= SEED;
    end else if (advance) begin
        state <= {state[13:0], feedback};
    end
end

endmodule

rtl/tx/optical_framer.sv
module optical_framer#(
    localparam logic [31:0] PREAMBLE = 32'hAAAAAAAA, // 10101010101010101010101010101010
    localparam logic [15:0] SYNC_WORD = 16'hD5B3, // 1101010110110011
    localparam logic [14:0] PRBS_SEED = 15'h0001 // 000000000000001
)
(
    input logic clk, 
    input logic rst, 
    input logic symbol_ce,
    input logic [1:0] mode,

    output logic tx_bit, frame_start, payload_start,
    output logic [15:0] frame_sequence
);

logic [9:0] field_index;
logic training_bit;
logic prbs_out;
logic prbs_load_seed;
logic prbs_advance;
logic [14:0] prbs_state;

prbs15_gen #(
    .SEED(PRBS_SEED)
) prbs_gen (
    .clk(clk),
    .rst(rst),
    .load_seed(prbs_load_seed),
    .advance(prbs_advance),
    .bit_out(prbs_out),
    .state(prbs_state)
);

typedef enum logic [1:0]{
    MODE_OFF = 2'b00,
    MODE_ON = 2'b01,
    MODE_TRAINING = 2'b10,
    MODE_FRAMED = 2'b11
} transmit_mode_t;

typedef enum logic [1:0] {
    FRAME_PREAMBLE,
    FRAME_SYNC,
    FRAME_SEQUENCE,
    FRAME_PAYLOAD
} frame_state_t;

frame_state_t frame_state;

logic framed_bit;

always_comb begin
    framed_bit = 1'b0;

    case (frame_state)
        FRAME_PREAMBLE:
            framed_bit = PREAMBLE[31 - field_index];

        FRAME_SYNC:
            framed_bit = SYNC_WORD[15 - field_index];

        FRAME_SEQUENCE:
            framed_bit = frame_sequence[15 - field_index];

        FRAME_PAYLOAD:
            framed_bit = prbs_out;

        default:
            framed_bit = 1'b0;
    endcase
end

always_comb begin
    if (rst) begin
        tx_bit = 1'b0;
    end else begin
        case (mode)
            MODE_OFF:
                tx_bit = 1'b0;

            MODE_ON:
                tx_bit = 1'b1;

            MODE_TRAINING:
                tx_bit = training_bit;

            MODE_FRAMED:
                tx_bit = framed_bit;

            default:
                tx_bit = 1'b0;
        endcase
    end
end

always_comb begin
    frame_start =
        symbol_ce &&
        (mode == MODE_FRAMED) &&
        (frame_state == FRAME_PREAMBLE) &&
        (field_index == 0);

    payload_start =
        symbol_ce &&
        (mode == MODE_FRAMED) &&
        (frame_state == FRAME_PAYLOAD) &&
        (field_index == 0);

    prbs_load_seed =
        symbol_ce &&
        (mode == MODE_FRAMED) &&
        (frame_state == FRAME_SEQUENCE) &&
        (field_index == 15);

    prbs_advance =
        symbol_ce &&
        (mode == MODE_FRAMED) &&
        (frame_state == FRAME_PAYLOAD);
end

always_ff @(posedge clk) begin
    if (rst) begin
        frame_state <= FRAME_PREAMBLE;
        field_index <= 10'd0;
        frame_sequence <= 16'd0;
        training_bit <= 1'b1;
    end else begin
        if (mode == MODE_TRAINING) begin
            if (symbol_ce) begin
                training_bit <= ~training_bit;
            end
        end else begin
            // Restart training at 1 next time it is selected.
            training_bit <= 1'b1;
        end

        if (mode != MODE_FRAMED) begin
            // Park the framer so framed mode always starts cleanly.
            frame_state <= FRAME_PREAMBLE;
            field_index <= 10'd0;
        end else if (symbol_ce) begin
            case (frame_state)
                FRAME_PREAMBLE: begin
                    if (field_index == 31) begin
                        frame_state <= FRAME_SYNC;
                        field_index <= 10'd0;
                    end else begin
                        field_index <= field_index + 10'd1;
                    end
                end

                FRAME_SYNC: begin
                    if (field_index == 15) begin
                        frame_state <= FRAME_SEQUENCE;
                        field_index <= 10'd0;
                    end else begin
                        field_index <= field_index + 10'd1;
                    end
                end

                FRAME_SEQUENCE: begin
                    if (field_index == 15) begin
                        frame_state <= FRAME_PAYLOAD;
                        field_index <= 10'd0;
                    end else begin
                        field_index <= field_index + 10'd1;
                    end
                end

                FRAME_PAYLOAD: begin
                    if (field_index == 1023) begin
                        frame_state <= FRAME_PREAMBLE;
                        field_index <= 10'd0;
                        frame_sequence <= frame_sequence + 16'd1;
                    end else begin
                        field_index <= field_index + 10'd1;
                    end
                end

                default: begin
                    frame_state <= FRAME_PREAMBLE;
                    field_index <= 10'd0;
                end
            endcase
        end
    end
end

endmodule

rtl/tb/tb_optical_framer_waveform.sv
`timescale 1ns/1ps

module tb_optical_framer_waveform;

logic clk = 1'b0;
logic rst = 1'b1;
logic symbol_ce = 1'b0;
logic [1:0] mode = 2'b00;
logic tx_bit;
logic frame_start;
logic payload_start;
logic [15:0] frame_sequence;

optical_framer dut (
    .clk(clk),
    .rst(rst),
    .symbol_ce(symbol_ce),
    .mode(mode),
    .tx_bit(tx_bit),
    .frame_start(frame_start),
    .payload_start(payload_start),
    .frame_sequence(frame_sequence)
);

always #5ns clk = ~clk;

initial begin
    repeat (2) @(posedge clk);
    @(negedge clk);
    rst = 1'b0;
    mode = 2'b11;

    repeat (36) begin
        symbol_ce = 1'b1;
        @(posedge clk);
        #1ns;
        @(negedge clk);
    end

    symbol_ce = 1'b0;
    repeat (3) @(posedge clk);
    @(negedge clk);

    repeat (34) begin
        symbol_ce = 1'b1;
        @(posedge clk);
        #1ns;
        @(negedge clk);
    end

    symbol_ce = 1'b0;
    repeat (3) @(posedge clk);
    $finish;
end

endmodule

docs/evidence/milestone-04/optical_framer_waveform.vcd
$date
   Wed Aug 12 20:29:34 2026
$end

$version
  2026.1
$end

$timescale
  1ps
$end

$scope module tb_optical_framer_waveform $end
$var reg 1 ! clk $end
$var reg 1 " rst $end
$var reg 1 # symbol_ce $end
$var reg 2 $ mode [1:0] $end
$var reg 1 % tx_bit $end
$var reg 1 & frame_start $end
$var reg 1 ' payload_start $end
$var reg 16 ( frame_sequence [15:0] $end
$scope module dut $end
$var reg 10 * field_index [9:0] $end
$var reg 1 + prbs_load_seed $end
$var reg 1 , prbs_advance $end
$var reg 2 ) frame_state $end
$upscope $end
$upscope $end
$enddefinitions $end

#0
$dumpvars
0!
1"
0#
b0 $
0%
0&
0'
bx (
bx )
bx *
0+
0,
$end

#5000
1!
b0 (
b0 )
b0 *

#10000
0!

#15000
1!

#20000
0!
0"
1#
b11 $
1%
1&

#25000
1!
0%
0&
b1 *

#30000
0!

#35000
1!
1%
b10 *

#40000
0!

#45000
1!
0%
b11 *

#50000
0!

#55000
1!
1%
b100 *

#60000
0!

#65000
1!
0%
b101 *

#70000
0!

#75000
1!
1%
b110 *

#80000
0!

#85000
1!
0%
b111 *

#90000
0!

#95000
1!
1%
b1000 *

#100000
0!

#105000
1!
0%
b1001 *

#110000
0!

#115000
1!
1%
b1010 *

#120000
0!

#125000
1!
0%
b1011 *

#130000
0!

#135000
1!
1%
b1100 *

#140000
0!

#145000
1!
0%
b1101 *

#150000
0!

#155000
1!
1%
b1110 *

#160000
0!

#165000
1!
0%
b1111 *

#170000
0!

#175000
1!
1%
b10000 *

#180000
0!

#185000
1!
0%
b10001 *

#190000
0!

#195000
1!
1%
b10010 *

#200000
0!

#205000
1!
0%
b10011 *

#210000
0!

#215000
1!
1%
b10100 *

#220000
0!

#225000
1!
0%
b10101 *

#230000
0!

#235000
1!
1%
b10110 *

#240000
0!

#245000
1!
0%
b10111 *

#250000
0!

#255000
1!
1%
b11000 *

#260000
0!

#265000
1!
0%
b11001 *

#270000
0!

#275000
1!
1%
b11010 *

#280000
0!

#285000
1!
0%
b11011 *

#290000
0!

#295000
1!
1%
b11100 *

#300000
0!

#305000
1!
0%
b11101 *

#310000
0!

#315000
1!
1%
b11110 *

#320000
0!

#325000
1!
0%
b11111 *

#330000
0!

#335000
1!
1%
b1 )
b0 *

#340000
0!

#345000
1!
b1 *

#350000
0!

#355000
1!
0%
b10 *

#360000
0!

#365000
1!
1%
b11 *

#370000
0!

#375000
1!
0%
b100 *

#380000
0!
0#

#385000
1!

#390000
0!

#395000
1!

#400000
0!

#405000
1!

#410000
0!
1#

#415000
1!
1%
b101 *

#420000
0!

#425000
1!
0%
b110 *

#430000
0!

#435000
1!
1%
b111 *

#440000
0!

#445000
1!
b1000 *

#450000
0!

#455000
1!
0%
b1001 *

#460000
0!

#465000
1!
1%
b1010 *

#470000
0!

#475000
1!
b1011 *

#480000
0!

#485000
1!
0%
b1100 *

#490000
0!

#495000
1!
b1101 *

#500000
0!

#505000
1!
1%
b1110 *

#510000
0!

#515000
1!
b1111 *

#520000
0!

#525000
1!
0%
b10 )
b0 *

#530000
0!

#535000
1!
b1 *

#540000
0!

#545000
1!
b10 *

#550000
0!

#555000
1!
b11 *

#560000
0!

#565000
1!
b100 *

#570000
0!

#575000
1!
b101 *

#580000
0!

#585000
1!
b110 *

#590000
0!

#595000
1!
b111 *

#600000
0!

#605000
1!
b1000 *

#610000
0!

#615000
1!
b1001 *

#620000
0!

#625000
1!
b1010 *

#630000
0!

#635000
1!
b1011 *

#640000
0!

#645000
1!
b1100 *

#650000
0!

#655000
1!
b1101 *

#660000
0!

#665000
1!
b1110 *

#670000
0!

#675000
1!
b1111 *
1+

#680000
0!

#685000
1!
1'
b11 )
b0 *
0+
1,

#690000
0!

#695000
1!
0'
b1 *

#700000
0!

#705000
1!
b10 *

#710000
0!

#715000
1!
b11 *

#720000
0!

#725000
1!
b100 *

#730000
0!

#735000
1!
b101 *

#740000
0!

#745000
1!
b110 *

#750000
0!
0#
0,

